{"numTotalTestSuites":2,"numPassedTestSuites":2,"numFailedTestSuites":0,"numPendingTestSuites":0,"numTotalTests":7,"numPassedTests":7,"numFailedTests":0,"numPendingTests":0,"numTodoTests":0,"snapshot":{"added":0,"failure":false,"filesAdded":0,"filesRemoved":0,"filesRemovedList":[],"filesUnmatched":0,"filesUpdated":0,"matched":0,"total":0,"unchecked":0,"uncheckedKeysByFile":[],"unmatched":0,"updated":0,"didUpdate":false},"startTime":1773071886939,"success":true,"testResults":[{"assertionResults":[{"ancestorTitles":["ProjectModal"],"fullName":"ProjectModal creates and opens project manage dialog","status":"passed","title":"creates and opens project manage dialog","duration":52.24669999999992,"failureMessages":[],"location":{"line":66,"column":5},"meta":{}},{"ancestorTitles":["ProjectModal"],"fullName":"ProjectModal updates project color on color button click","status":"passed","title":"updates project color on color button click","duration":14.667999999999893,"failureMessages":[],"location":{"line":77,"column":5},"meta":{}},{"ancestorTitles":["ProjectModal"],"fullName":"ProjectModal keeps modal renderable when one task-count query fails","status":"passed","title":"keeps modal renderable when one task-count query fails","duration":8.351100000000088,"failureMessages":[],"location":{"line":94,"column":5},"meta":{}},{"ancestorTitles":["ProjectModal"],"fullName":"ProjectModal does not rename when input is empty and restores previous value","status":"passed","title":"does not rename when input is empty and restores previous value","duration":6.096900000000005,"failureMessages":[],"location":{"line":113,"column":5},"meta":{}},{"ancestorTitles":["ProjectModal"],"fullName":"ProjectModal renames project on input blur and dispatches projectsUpdated","status":"passed","title":"renames project on input blur and dispatches projectsUpdated","duration":4.5516999999999825,"failureMessages":[],"location":{"line":128,"column":5},"meta":{}},{"ancestorTitles":["ProjectModal"],"fullName":"ProjectModal deletes current project and switches to first remaining project","status":"passed","title":"deletes current project and switches to first remaining project","duration":6.05600000000004,"failureMessages":[],"location":{"line":145,"column":5},"meta":{}},{"ancestorTitles":["ProjectModal"],"fullName":"ProjectModal deletes non-current project without switching current project","status":"passed","title":"deletes non-current project without switching current project","duration":9.59880000000021,"failureMessages":[],"location":{"line":164,"column":5},"meta":{}}],"startTime":1773071888312,"endTime":1773071888414.5989,"status":"passed","message":"","name":"C:/Users/24408/Desktop/新建文件夹/tests/unit/projects-modal.test.js"}]}